{"post_max_cnt": 1749, "statistics": [{"date": "00", "posts": 403, "comments": 3778}, {"date": "01", "posts": 281, "comments": 2468}, {"date": "02", "posts": 179, "comments": 1262}, {"date": "03", "posts": 82, "comments": 725}, {"date": "04", "posts": 52, "comments": 373}, {"date": "05", "posts": 65, "comments": 385}, {"date": "06", "posts": 91, "comments": 474}, {"date": "07", "posts": 197, "comments": 1255}, {"date": "08", "posts": 694, "comments": 3541}, {"date": "09", "posts": 1264, "comments": 8367}, {"date": "10", "posts": 1661, "comments": 11406}, {"date": "11", "posts": 1749, "comments": 12028}, {"date": "12", "posts": 977, "comments": 7073}, {"date": "13", "posts": 1416, "comments": 9934}, {"date": "14", "posts": 1555, "comments": 10184}, {"date": "15", "posts": 1500, "comments": 10819}, {"date": "16", "posts": 1555, "comments": 11678}, {"date": "17", "posts": 1438, "comments": 11518}, {"date": "18", "posts": 1083, "comments": 8662}, {"date": "19", "posts": 620, "comments": 4882}, {"date": "20", "posts": 494, "comments": 3889}, {"date": "21", "posts": 535, "comments": 4157}, {"date": "22", "posts": 546, "comments": 4437}, {"date": "23", "posts": 525, "comments": 4516}], "comment_max_cnt": 12028}